simple_ctx_log/__init__.py
simple_ctx_log/logger.py
simple_ctx_log-0.2.0.dist-info/METADATA
simple_ctx_log-0.2.0.dist-info/WHEEL
simple_ctx_log-0.2.0.dist-info/licenses/LICENSE.txt
simple_ctx_log-0.2.0.dist-info/RECORD
