Metadata-Version: 2.4
Name: simple_ctx_log
Version: 0.2.0
Summary: Simple contextual logger
Project-URL: Documentation, https://github.com/Hactys/simple_ctx_log#readme
Project-URL: Issues, https://github.com/Hactys/simple_ctx_log/issues
Project-URL: Source, https://github.com/Hactys/simple_ctx_log
Author: Hactys
License-Expression: MIT
License-File: LICENSE.txt
Classifier: Development Status :: 4 - Beta
Classifier: Programming Language :: Python
Classifier: Programming Language :: Python :: 3.10
Classifier: Programming Language :: Python :: 3.11
Classifier: Programming Language :: Python :: 3.12
Classifier: Programming Language :: Python :: 3.13
Classifier: Programming Language :: Python :: 3.14
Classifier: Programming Language :: Python :: Implementation :: CPython
Classifier: Programming Language :: Python :: Implementation :: PyPy
Requires-Python: >=3.10
